README
setup.py
south_jurisdiction/__init__.py
south_jurisdiction.egg-info/PKG-INFO
south_jurisdiction.egg-info/SOURCES.txt
south_jurisdiction.egg-info/dependency_links.txt
south_jurisdiction.egg-info/requires.txt
south_jurisdiction.egg-info/top_level.txt
south_jurisdiction/management/__init__.py
south_jurisdiction/management/commands/__init__.py
south_jurisdiction/management/commands/migrate.py