Metadata-Version: 1.0
Name: south-jurisdiction
Version: 0.1.1
Summary: South Migrations with database jurisdictions for Django
Home-page: https://github.com/alexcouper/django-south-jurisdiction/
Author: Alex Couper
Author-email: amcouper@gmail.com
License: UNKNOWN
Platform: UNKNOWN
Classifier: Development Status :: 4 - Beta
Classifier: Framework :: Django
Classifier: Intended Audience :: Developers
Classifier: Intended Audience :: System Administrators
Classifier: Intended Audience :: System Administrators
Classifier: License :: OSI Approved :: Apache Software License
Classifier: Operating System :: OS Independent
Classifier: Topic :: Software Development
